permutation/__init__.py
permutation/permutation.py
dowell_permutation-0.1.1.dist-info/METADATA
dowell_permutation-0.1.1.dist-info/WHEEL
dowell_permutation-0.1.1.dist-info/top_level.txt
dowell_permutation-0.1.1.dist-info/RECORD
