Metadata-Version: 2.1
Name: dowell-permutation
Version: 0.1.1
Summary: Dowell Permutation API Python Libray
Home-page: https://dowell-permutation.readthedocs.io/en/latest/
Author: Dennis RK.
License: MIT
Platform: UNKNOWN
Requires-Dist: requests
